Pyesian/__init__.py
Pyesian/requirements.txt
Pyesian/datasets/Dataset.py
Pyesian/datasets/__init__.py
Pyesian/datasets/utils.py
Pyesian/distributions/Distribution.py
Pyesian/distributions/DistributionSerializer.py
Pyesian/distributions/GaussianPrior.py
Pyesian/distributions/MultivariateNormalDiagPlusLowRank.py
Pyesian/distributions/Sampled.py
Pyesian/distributions/__init__.py
Pyesian/distributions/tf/BaseSerializer.py
Pyesian/distributions/tf/Constant.py
Pyesian/distributions/tf/TensorflowProbabilityDistribution.py
Pyesian/distributions/tf/__init__.py
Pyesian/dynamics/DeepPilco.py
Pyesian/dynamics/Policy.py
Pyesian/dynamics/PolicyNN.py
Pyesian/dynamics/__init__.py
Pyesian/dynamics/control.py
Pyesian/dynamics/custom.py
Pyesian/dynamics/deep_pilco.py
Pyesian/nn/BayesianModel.py
Pyesian/nn/__init__.py
Pyesian/optimizers/ADAM.py
Pyesian/optimizers/BBB.py
Pyesian/optimizers/BSAM.py
Pyesian/optimizers/HMC.py
Pyesian/optimizers/Optimizer.py
Pyesian/optimizers/SGD.py
Pyesian/optimizers/SGLD.py
Pyesian/optimizers/SWAG.py
Pyesian/optimizers/VADAM.py
Pyesian/optimizers/__init__.py
Pyesian/optimizers/hyperparameters/GridOptimizer.py
Pyesian/optimizers/hyperparameters/HyperParameters.py
Pyesian/optimizers/hyperparameters/HyperparameterOptimizer.py
Pyesian/optimizers/hyperparameters/WandbHyperparametersOptimizer.py
Pyesian/optimizers/hyperparameters/__init__.py
Pyesian/optimizers/hyperparameters/space.py
Pyesian/visualisations/Metrics.py
Pyesian/visualisations/Plotter.py
Pyesian/visualisations/Robustness.py
Pyesian/visualisations/__init__.py
pyesian-0.0.1.1.dist-info/WHEEL
pyesian-0.0.1.1.dist-info/METADATA
pyesian-0.0.1.1.dist-info/RECORD
