Metadata-Version: 2.1
Name: Pyesian
Version: 0.0.1.1
Summary: A framework for Bayesian Neural Nets
Requires-Python: >=3.5
Project-URL: Homepage, https://github.com/HassenAissa/Bayesian_inference_for_NN
